CountingNN/__init__.py
CountingNN/anchor_custom.py
CountingNN/blocks.py
CountingNN/dataset.py
CountingNN/faster_rcnn_custom.py
CountingNN/fcn.py
CountingNN/generalized_rcnn_custom.py
CountingNN/locator.py
CountingNN/locator_archive.py
CountingNN/model.py
CountingNN/roi_heads_custom.py
CountingNN/rpn_custom.py
CountingNN/train.py
CountingNN/transform_custom.py
CountingNN/validator.py
CountingNN/archive/__init__.py
CountingNN/archive/box_ops.py
CountingNN/archive/gpu.py
CountingNN/archive/mask_rcnn.py
CountingNN/archive/pooler.py
CountingNN/archive/roi_heads.py
CountingNN/archive/rpn.py
CountingNN/archive/train_archive.py
CountingNN/archive/transform.py
CountingNN/archive/utils.py
CountingNN/modelweights/__init__.py
CountingNN/modelweights/model_200kV_final.pt
CountingNN/modelweights/model_80kV_final.pt
ElectronCounting-1.0.0.dist-info/METADATA
ElectronCounting-1.0.0.dist-info/WHEEL
ElectronCounting-1.0.0.dist-info/top_level.txt
ElectronCounting-1.0.0.dist-info/RECORD
