Metadata-Version: 2.1
Name: ElectronCounting
Version: 1.0.0
Summary: Count single electron in direct electron detector data
Home-page: https://github.com/wdwzyyg/ElectronCounting.git
Author: Jingrui Wei
Author-email: jwei74@wisc.edu
License: MIT
Keywords: direct electron detector,electron microscopy,data analysis,object detection,Faster R-CNN
Requires-Dist: torch (==1.12.0)
Requires-Dist: torchvision (==0.13.0)
Requires-Dist: numpy (>=1.20.1)
